<!-- 
GAME VERSION: v.100.19.5934.0,
GAME BUILD: 22410022,
GAME VERSION RELEASE DATE: 24 March 2026 
-->

<protomods>
<!-- GREEK UNIT -->
	<!-- UNIT: VILLAGER GREEK -->
	<unit name="VillagerGreek">
		<cost mergeMode="modify" resourcetype="Food"></cost>
	</unit>

<!-- EGYPTIAN UNIT -->
	<!-- UNIT: LABORER -->
	<unit name="VillagerEgyptian">
		<cost mergeMode="modify" resourcetype="Food"></cost>
	</unit>

<!-- NORSE UNIT -->
	<!-- UNIT: GATHERER -->
	<unit name="VillagerNorse">
		<cost mergeMode="modify" resourcetype="Food"></cost>
	</unit>

<!-- ATLANTEAN UNIT -->
	<!-- UNIT: CITIZEN -->
	<unit name="VillagerAtlantean">
		<cost mergeMode="modify" resourcetype="Food"></cost>
	</unit>

<!-- CHINESE UNIT -->
	<!-- UNIT: PEASANT -->
	<unit name="VillagerChinese">
		<cost mergeMode="modify" resourcetype="Food"></cost>
	</unit>

<!-- JAPANESE UNIT -->
	<!-- UNIT: PEASANT -->
	<unit name="VillagerJapanese">
		<cost mergeMode="modify" resourcetype="Food"></cost>
	</unit>

</protomods>